{
  "livescore": 520116,
  "gift": [
    93032,
    50201,
    15001,
    14280,
    3010,
    1920,
    1281,
    1160,
    1121,
    1001,
    1000,
    1000,
    1000,
    1000,
    600,
    600,
    340,
    310,
    270,
    110,
    101,
    100,
    100,
    81,
    81,
    51,
    21,
    10,
    10,
    10,
    10,
    1,
    0,
    0,
    0,
    0,
    0,
    0,
    0,
    0
  ],
  "date": "20251103",
  "rank": 16,
  "label": "16",
  "user_rank": "A2",
  "following": 359,
  "followers": 478,
  "name": "絶狂ちゃんぶ@⑱ハフアニ最終日"
}