{
  "livescore": 132481,
  "gift": [
    17201,
    3020,
    2211,
    2010,
    2000,
    2000,
    1951,
    1231,
    1200,
    1150,
    1110,
    1070,
    1060,
    1000,
    1000,
    1000,
    1000,
    500,
    201,
    160,
    130,
    120,
    110,
    100,
    100,
    90,
    40,
    30,
    10,
    10,
    10,
    10,
    10,
    10,
    10,
    1,
    1,
    1,
    0,
    0,
    0,
    0,
    0,
    0,
    0,
    0,
    0,
    0,
    0,
    0,
    0,
    0,
    0,
    0,
    0,
    0,
    0,
    0,
    0,
    0,
    0,
    0
  ],
  "date": "20251105",
  "rank": 34,
  "label": "34",
  "user_rank": "A5",
  "following": 20,
  "followers": 1886,
  "name": "よら) .役0"
}