{
  "livescore": 127515,
  "gift": [
    9001,
    6610,
    6231,
    5000,
    4131,
    2030,
    2030,
    1400,
    1131,
    1010,
    1000,
    490,
    310,
    220,
    200,
    121,
    111,
    100,
    100,
    100,
    100,
    40,
    11,
    10,
    10,
    10,
    10,
    10,
    0,
    0,
    0,
    0,
    0,
    0,
    0,
    0,
    0,
    0,
    0,
    0,
    0
  ],
  "date": "20251104",
  "rank": 31,
  "label": "31",
  "user_rank": "A2",
  "following": 79,
  "followers": 366,
  "name": "しき|"
}