{
  "livescore": 269144,
  "gift": [
    39641,
    12180,
    7140,
    5200,
    5001,
    5000,
    4001,
    1500,
    1010,
    1001,
    1000,
    1000,
    1000,
    1000,
    1000,
    1000,
    990,
    660,
    531,
    510,
    500,
    431,
    300,
    130,
    110,
    110,
    100,
    100,
    100,
    100,
    100,
    100,
    100,
    60,
    40,
    40,
    30,
    20,
    20,
    20,
    20,
    10,
    10,
    10,
    10,
    10,
    10,
    10,
    10,
    10,
    10,
    0,
    0,
    0,
    0,
    0,
    0,
    0,
    0,
    0,
    0,
    0,
    0,
    0,
    0,
    0,
    0,
    0,
    0,
    0,
    0,
    0,
    0,
    0,
    0,
    0,
    0,
    0,
    0
  ],
  "date": "20251017",
  "rank": 7,
  "label": "7"
}