{
  "livescore": 274897,
  "gift": [
    50042,
    22300,
    10531,
    1482,
    1160,
    1111,
    1100,
    1040,
    1001,
    1000,
    940,
    520,
    470,
    370,
    370,
    260,
    210,
    200,
    200,
    141,
    111,
    101,
    101,
    100,
    100,
    100,
    100,
    50,
    40,
    20,
    10,
    10,
    10,
    1,
    1,
    1,
    1,
    1,
    1,
    1,
    1,
    0,
    0,
    0,
    0,
    0,
    0,
    0,
    0,
    0,
    0,
    0,
    0,
    0
  ],
  "date": "20251027",
  "rank": 21,
  "label": "21",
  "user_rank": "A2",
  "following": 416,
  "followers": 920,
  "name": "pcと アノ"
}