{
  "livescore": 180837,
  "gift": [
    30800,
    15740,
    14000,
    1060,
    110,
    101,
    81,
    60,
    20,
    10,
    10,
    10,
    10,
    10,
    10,
    1,
    0,
    0,
    0,
    0,
    0,
    0,
    0,
    0,
    0,
    0,
    0,
    0,
    0,
    0,
    0,
    0,
    0,
    0,
    0,
    0,
    0,
    0,
    0,
    0,
    0,
    0,
    0,
    0
  ],
  "date": "20251026",
  "rank": 12,
  "label": "12",
  "user_rank": "A3",
  "following": 69,
  "followers": 748,
  "name": "(克:上"
}