{
  "livescore": 87103,
  "gift": [
    7300,
    4701,
    2660,
    1490,
    1000,
    770,
    770,
    660,
    660,
    640,
    620,
    540,
    540,
    340,
    340,
    330,
    240,
    220,
    210,
    200,
    200,
    200,
    200,
    200,
    180,
    180,
    170,
    160,
    140,
    130,
    110,
    110,
    100,
    100,
    100,
    100,
    100,
    100,
    90,
    40,
    40,
    30,
    20,
    20,
    10,
    10,
    10,
    1,
    0,
    0,
    0,
    0,
    0,
    0,
    0,
    0,
    0,
    0,
    0,
    0,
    0,
    0,
    0,
    0,
    0,
    0
  ],
  "date": "20251026",
  "rank": 55,
  "label": "55",
  "user_rank": "A1",
  "following": 201,
  "followers": 551,
  "name": "maa=ル7の"
}