{
  "livescore": 204812,
  "gift": [
    13501,
    11001,
    6000,
    5000,
    4000,
    2000,
    1540,
    1230,
    1090,
    1020,
    1011,
    1011,
    1010,
    1001,
    1000,
    1000,
    1000,
    1000,
    1000,
    1000,
    1000,
    1000,
    1000,
    1000,
    1000,
    1000,
    1000,
    1000,
    1000,
    1000,
    1000,
    500,
    101,
    100,
    20,
    10,
    10,
    10,
    10,
    1,
    1,
    0,
    0,
    0,
    0,
    0,
    0,
    0,
    0,
    0,
    0,
    0,
    0,
    0,
    0,
    0,
    0,
    0,
    0,
    0,
    0,
    0,
    0,
    0,
    0,
    0,
    0,
    0,
    0,
    0,
    0,
    0,
    0,
    0,
    0,
    0
  ],
  "date": "20251101",
  "rank": 30,
  "label": "30",
  "user_rank": "B3",
  "following": 217,
  "followers": 319,
  "name": "AA にne"
}